LICENSE
README.md
setup.cfg
setup.py
TOPSIS_ANKITAPURI_101903766.egg-info/PKG-INFO
TOPSIS_ANKITAPURI_101903766.egg-info/SOURCES.txt
TOPSIS_ANKITAPURI_101903766.egg-info/dependency_links.txt
TOPSIS_ANKITAPURI_101903766.egg-info/entry_points.txt
TOPSIS_ANKITAPURI_101903766.egg-info/requires.txt
TOPSIS_ANKITAPURI_101903766.egg-info/top_level.txt
topsis_test_101/101903766.py